orbis_plugin_aggregation_recognize/__init__.py
orbis_plugin_aggregation_recognize/main.py
orbis_plugin_aggregation_recognize-0.1.0.dist-info/LICENSE
orbis_plugin_aggregation_recognize-0.1.0.dist-info/METADATA
orbis_plugin_aggregation_recognize-0.1.0.dist-info/WHEEL
orbis_plugin_aggregation_recognize-0.1.0.dist-info/top_level.txt
orbis_plugin_aggregation_recognize-0.1.0.dist-info/RECORD
