Metadata-Version: 2.1
Name: orbis-plugin-aggregation-recognize
Version: 0.1.0
Summary: The spotlight aggregation plugin for Orbis
Home-page: https://github.com/orbis-eval/orbis_plugin_aggregation_recognize
Author: Albert Weichselbraun
License: GPL3
Platform: UNKNOWN
Requires-Python: >3.6
Requires-Dist: requests
